libfast_perlin_noise.cp310-win_amd64.h
libfast_perlin_noise.cp310-win_amd64.pyd
fast_perlin_noise/PerlinNoise.py
fast_perlin_noise/__init__.py
fast_perlin_noise/_version.py
fast_perlin_noise-1.1.2.dist-info/LICENSE
fast_perlin_noise-1.1.2.dist-info/METADATA
fast_perlin_noise-1.1.2.dist-info/WHEEL
fast_perlin_noise-1.1.2.dist-info/top_level.txt
fast_perlin_noise-1.1.2.dist-info/RECORD
