Metadata-Version: 2.1
Name: fast_perlin_noise
Version: 1.1.2
Summary: A simple and fast Perlin noise generation library
Author-email: Joshua Riefman <joshuariefman@gmail.com>
Maintainer-email: Joshua Riefman <joshuariefman@gmail.com>
License:                     GNU GENERAL PUBLIC LICENSE
Project-URL: Repository, https://github.com/joshuaRiefman/fast_perlin_noise
Keywords: perlin-noise,noise,go
Classifier: Programming Language :: Python :: 3
Classifier: Natural Language :: English
Classifier: Topic :: Scientific/Engineering :: Physics
Requires-Python: >=3.9
License-File: LICENSE
Requires-Dist: numpy
Requires-Dist: strenum
